sparsereg/__init__.py
sparsereg/_version.py
sparsereg/model/__init__.py
sparsereg/model/base.py
sparsereg/model/bayes.py
sparsereg/model/efs.py
sparsereg/model/ffx.py
sparsereg/model/group_lasso.py
sparsereg/model/sindy.py
sparsereg/preprocessing/__init__.py
sparsereg/preprocessing/symfeat.py
sparsereg/util/__init__.py
sparsereg/util/net.py
sparsereg/util/pipeline.py
sparsereg/vendor/__init__.py
sparsereg/vendor/group_lasso/__init__.py
sparsereg/vendor/group_lasso/group_lasso.py
sparsereg-0.10.0.dist-info/LICENSE
sparsereg-0.10.0.dist-info/METADATA
sparsereg-0.10.0.dist-info/WHEEL
sparsereg-0.10.0.dist-info/top_level.txt
sparsereg-0.10.0.dist-info/RECORD
