Metadata-Version: 1.2
Name: sparsereg
Version: 0.10.0
Summary: Modern sparse linear regression
Home-page: https://github.com/ohjeah/sparsereg
Author: Markus Quade
Author-email: info@markusqua.de
License: MIT
Platform: UNKNOWN
Classifier: Programming Language :: Python
Classifier: Programming Language :: Python :: 3.6
Classifier: Development Status :: 4 - Beta
Classifier: Intended Audience :: Science/Research
Classifier: License :: OSI Approved :: GNU Lesser General Public License v3 (LGPLv3)
Classifier: Topic :: Scientific/Engineering :: Mathematics
Requires-Python: >=3.6
